aep_parser/__init__.py
aep_parser/cos/__init__.py
aep_parser/cos/cos.py
aep_parser/kaitai/__init__.py
aep_parser/kaitai/aep.py
aep_parser/kaitai/utils.py
aep_parser/models/__init__.py
aep_parser/models/project.py
aep_parser/models/items/__init__.py
aep_parser/models/items/av_item.py
aep_parser/models/items/composition.py
aep_parser/models/items/folder.py
aep_parser/models/items/footage.py
aep_parser/models/items/item.py
aep_parser/models/layers/__init__.py
aep_parser/models/layers/av_layer.py
aep_parser/models/layers/layer.py
aep_parser/models/layers/light_layer.py
aep_parser/models/properties/__init__.py
aep_parser/models/properties/keyframe.py
aep_parser/models/properties/marker.py
aep_parser/models/properties/property.py
aep_parser/models/properties/property_base.py
aep_parser/models/properties/property_group.py
aep_parser/models/sources/__init__.py
aep_parser/models/sources/file.py
aep_parser/models/sources/footage.py
aep_parser/models/sources/placeholder.py
aep_parser/models/sources/solid.py
aep_parser/parsers/__init__.py
aep_parser/parsers/composition.py
aep_parser/parsers/footage.py
aep_parser/parsers/item.py
aep_parser/parsers/layer.py
aep_parser/parsers/project.py
aep_parser/parsers/property.py
aep_parser/parsers/utils.py
aep_parser-0.0.3.dist-info/METADATA
aep_parser-0.0.3.dist-info/WHEEL
aep_parser-0.0.3.dist-info/top_level.txt
aep_parser-0.0.3.dist-info/RECORD
