Metadata-Version: 2.1
Name: aep-parser
Version: 0.0.3
Summary: A .aep (After Effects Project) parser
Home-page: UNKNOWN
Author: Benoit Delaunay
Author-email: delaunay.ben@gmail.com
License: MIT
Platform: UNKNOWN
Classifier: Development Status :: 3 - Alpha
Classifier: License :: OSI Approved :: MIT License
Classifier: Operating System :: OS Independent
Classifier: Programming Language :: Python :: 2
Classifier: Programming Language :: Python :: 2.7
Classifier: Programming Language :: Python :: 3
Classifier: Programming Language :: Python :: 3.0
Classifier: Programming Language :: Python :: 3.1
Classifier: Programming Language :: Python :: 3.2
Classifier: Programming Language :: Python :: 3.3
Classifier: Programming Language :: Python :: 3.4
Classifier: Programming Language :: Python :: 3.5
Classifier: Programming Language :: Python :: 3.6
Classifier: Programming Language :: Python :: 3.7
Classifier: Programming Language :: Python :: 3.8
Classifier: Programming Language :: Python :: 3.9
Classifier: Programming Language :: Python :: 3.10
Classifier: Programming Language :: Python :: 3.11
Classifier: Topic :: File Formats
Classifier: Topic :: Multimedia :: Graphics
Requires-Python: >=2.7
Requires-Dist: kaitaistruct (>=0.9)
Requires-Dist: future ; python_version < "3.0"
Requires-Dist: six ; python_version < "3.0"
Requires-Dist: enum34 ; python_version < "3.4"
